pysocksproto/__init__.py
pysocksproto/constants.py
pysocksproto/exceptions.py
pysocksproto/pysocksproto.py
pysocksproto/socksproto.py
pysocksproto/tools.py
pysocksproto-0.1.0.dist-info/LICENSE
pysocksproto-0.1.0.dist-info/METADATA
pysocksproto-0.1.0.dist-info/WHEEL
pysocksproto-0.1.0.dist-info/top_level.txt
pysocksproto-0.1.0.dist-info/RECORD
