Metadata-Version: 2.1
Name: pysocksproto
Version: 0.1.0
Summary: Customizable python module for create your own programs on SOCKS protocol 
Home-page: https://github.com/fkohs/py_socksproto
Author: Daniil Tumanov
Author-email: fkohs@inbox.ru
License: UNKNOWN
Platform: UNKNOWN
Classifier: Programming Language :: Python :: 3.6
Classifier: License :: OSI Approved :: MIT License
Classifier: Operating System :: OS Independent
Requires-Python: >=3.6
